MANIFEST.in
setup.py
django_pjm/__init__.py
django_pjm/admin.py
django_pjm/constants.py
django_pjm/models.py
django_pjm/settings.py
django_pjm.egg-info/PKG-INFO
django_pjm.egg-info/SOURCES.txt
django_pjm.egg-info/dependency_links.txt
django_pjm.egg-info/not-zip-safe
django_pjm.egg-info/requires.txt
django_pjm.egg-info/top_level.txt
django_pjm/management/__init__.py
django_pjm/management/commands/__init__.py
django_pjm/management/commands/import_pjm_loads.py
django_pjm/management/commands/import_pjm_prices.py
django_pjm/migrations/0001_initial.py
django_pjm/migrations/0002_auto__add_field_lmpda_hour.py
django_pjm/migrations/0003_auto__add_lmpdastatus.py
django_pjm/migrations/0004_auto__add_field_lmpda_day_ahead__del_unique_lmpda_node_start_datetime_.py
django_pjm/migrations/0005_auto__add_load__add_unique_load_node_station_start_datetime_end_dateti.py
django_pjm/migrations/0006_auto__del_field_load_station__del_unique_load_node_station_start_datet.py
django_pjm/migrations/__init__.py
django_pjm/reference/ppl/ProfileEquations_2005-cropped.txt.gz
django_pjm/reference/ppl/ProfileEquations_2006-cropped.txt.gz
django_pjm/reference/ppl/ProfileEquations_2007-cropped.txt.gz
django_pjm/reference/ppl/ProfileEquations_2008-cropped.txt.gz
django_pjm/reference/ppl/ProfileEquations_2009-cropped.txt.gz
django_pjm/reference/ppl/ProfileEquations_2010-cropped.txt.gz
django_pjm/reference/ppl/ProfileEquations_2011-cropped.txt.gz
django_pjm/reference/ppl/ProfileEquations_2012-cropped.txt.gz
django_pjm/reference/ppl/ProfileEquations_2013-cropped.txt.gz
django_pjm/reference/ppl/ProfileEquations_2014-cropped.txt.gz
django_pjm/reference/ppl/README.md