Metadata-Version: 1.1
Name: django-pjm
Version: 0.2.4
Summary: A Django app for managing public PJM energy pricing data.
Home-page: https://github.com/chrisspen/django-pjm
Author: Chris Spencer
Author-email: chrisspen@gmail.com
License: MIT
Platform: UNKNOWN
Classifier: Environment :: Web Environment
Classifier: Intended Audience :: Developers
Classifier: License :: OSI Approved :: MIT License
Classifier: Operating System :: OS Independent
Classifier: Programming Language :: Python
Classifier: Framework :: Django
Classifier: License :: OSI Approved :: GNU Lesser General Public License v3 (LGPLv3)
Classifier: Development Status :: 4 - Beta
